{
    "key": "group_5f9f018a75c7a",
    "title": "About Page Options",
    "fields": [
        {
            "key": "field_5f9f1e19f9929",
            "label": "Introduction",
            "name": "introduction",
            "aria-label": "",
            "type": "textarea",
            "instructions": "",
            "required": 0,
            "conditional_logic": 0,
            "wrapper": {
                "width": "",
                "class": "",
                "id": ""
            },
            "default_value": "",
            "placeholder": "",
            "maxlength": "",
            "rows": 2,
            "new_lines": ""
        },
        {
            "key": "field_5fcea53d902a7",
            "label": "Catchphrase",
            "name": "catchphrase",
            "aria-label": "",
            "type": "text",
            "instructions": "",
            "required": 0,
            "conditional_logic": 0,
            "wrapper": {
                "width": "",
                "class": "",
                "id": ""
            },
            "default_value": "",
            "placeholder": "",
            "prepend": "",
            "append": "",
            "maxlength": ""
        },
        {
            "key": "field_5fa2f1e54c49d",
            "label": "Images",
            "name": "images",
            "aria-label": "",
            "type": "gallery",
            "instructions": "",
            "required": 0,
            "conditional_logic": 0,
            "wrapper": {
                "width": "",
                "class": "",
                "id": ""
            },
            "return_format": "array",
            "preview_size": "medium",
            "insert": "append",
            "library": "all",
            "min": "",
            "max": 4,
            "min_width": "",
            "min_height": "",
            "min_size": "",
            "max_width": "",
            "max_height": "",
            "max_size": "",
            "mime_types": ""
        },
        {
            "key": "field_5fd0b1437b610",
            "label": "Map",
            "name": "map",
            "aria-label": "",
            "type": "group",
            "instructions": "",
            "required": 0,
            "conditional_logic": 0,
            "wrapper": {
                "width": "",
                "class": "",
                "id": ""
            },
            "layout": "block",
            "sub_fields": [
                {
                    "key": "field_5fd0b1517b611",
                    "label": "Contenu",
                    "name": "content",
                    "aria-label": "",
                    "type": "textarea",
                    "instructions": "",
                    "required": 0,
                    "conditional_logic": 0,
                    "wrapper": {
                        "width": "",
                        "class": "",
                        "id": ""
                    },
                    "default_value": "",
                    "placeholder": "",
                    "maxlength": "",
                    "rows": 4,
                    "new_lines": "br"
                }
            ]
        },
        {
            "key": "field_5f9f01db1b793",
            "label": "FAQ",
            "name": "faq",
            "aria-label": "",
            "type": "repeater",
            "instructions": "",
            "required": 0,
            "conditional_logic": 0,
            "wrapper": {
                "width": "",
                "class": "",
                "id": ""
            },
            "collapsed": "",
            "min": 0,
            "max": 0,
            "layout": "block",
            "button_label": "Ajouter une question",
            "sub_fields": [
                {
                    "key": "field_5f9f01f31b794",
                    "label": "Question",
                    "name": "question",
                    "aria-label": "",
                    "type": "textarea",
                    "instructions": "",
                    "required": 0,
                    "conditional_logic": 0,
                    "wrapper": {
                        "width": "",
                        "class": "",
                        "id": ""
                    },
                    "default_value": "",
                    "placeholder": "",
                    "maxlength": "",
                    "rows": 2,
                    "new_lines": "",
                    "parent_repeater": "field_5f9f01db1b793"
                },
                {
                    "key": "field_5f9f023c1b795",
                    "label": "Réponse",
                    "name": "answer",
                    "aria-label": "",
                    "type": "textarea",
                    "instructions": "",
                    "required": 0,
                    "conditional_logic": 0,
                    "wrapper": {
                        "width": "",
                        "class": "",
                        "id": ""
                    },
                    "default_value": "",
                    "placeholder": "",
                    "maxlength": "",
                    "rows": "",
                    "new_lines": "wpautop",
                    "parent_repeater": "field_5f9f01db1b793"
                }
            ],
            "rows_per_page": 20
        }
    ],
    "location": [
        [
            {
                "param": "page_template",
                "operator": "==",
                "value": "templates\/about-page.php"
            }
        ]
    ],
    "menu_order": 0,
    "position": "normal",
    "style": "default",
    "label_placement": "top",
    "instruction_placement": "label",
    "hide_on_screen": "",
    "active": true,
    "description": "Options de la page À propos",
    "show_in_rest": 0,
    "modified": 1683026590
}